qpay/__init__.py
qpay/auth.py
qpay/exceptions.py
qpay/main.py
qpay/singleton.py
qpay_python-0.0.5.dist-info/METADATA
qpay_python-0.0.5.dist-info/WHEEL
qpay_python-0.0.5.dist-info/RECORD
