Metadata-Version: 2.3
Name: qpay-python
Version: 0.0.5
Summary: QPay v2 SDK client for Python projects
License: MIT
Keywords: python,qpay,sdk,payment,qr,finance
Author: khasbilegt
Author-email: khasbilegt.ts@gmail.com
Requires-Python: >=3.9,<4.0
Classifier: Framework :: Pydantic
Classifier: Framework :: Pytest
Classifier: Intended Audience :: Developers
Classifier: License :: OSI Approved :: MIT License
Classifier: Programming Language :: Python
Classifier: Programming Language :: Python :: 3
Classifier: Programming Language :: Python :: 3.9
Classifier: Programming Language :: Python :: 3.10
Classifier: Programming Language :: Python :: 3.11
Classifier: Programming Language :: Python :: 3.12
Classifier: Programming Language :: Python :: 3.13
Classifier: Topic :: Software Development :: Build Tools
Classifier: Typing :: Typed
Requires-Dist: pydantic (>=2.7.0,<3.0.0)
Requires-Dist: requests (>=2.31.0,<3.0.0)
Project-URL: Homepage, https://github.com/khasbilegt/qpay-python
Project-URL: Repository, https://github.com/khasbilegt/qpay-python
